ahapi/__init__.py
ahapi/formdata.py
ahapi/server.py
ahapi/session.py
ahapi-0.1.18.dist-info/METADATA
ahapi-0.1.18.dist-info/WHEEL
ahapi-0.1.18.dist-info/top_level.txt
ahapi-0.1.18.dist-info/zip-safe
ahapi-0.1.18.dist-info/RECORD
