Metadata-Version: 2.1
Name: ahapi
Version: 0.1.18
Summary: Asynchronous HTTP API Server
Home-page: https://github.com/Humbedooh/ahapi
Author: Daniel Gruno
Author-email: humbedooh@apache.org
License: Apache
Platform: UNKNOWN
Requires-Dist: aiohttp
Requires-Dist: multipart
